[
    {
        "id": 1,
        "question": "",
        "options": [
            "",
            "",
            "",
            ""
        ],
        "correct": 0,
        "image": null
    },
    {
        "id": 2,
        "question": "",
        "options": [
            "",
            "",
            "",
            "",
            ""
        ],
        "correct": 0,
        "image": "133.jpg"
    },
    {
        "id": 3,
        "question": "",
        "left_items": ["", "", ""],
        "right_items": ["", "", "", ""],
        "correct_matches": [[0, 0], [1, 1], [2, 2]],
        "image": null,
        "type": "matching"
    },
]